{
	"name": "houseprice",
	"properties": {
		"linkedServiceName": {
			"referenceName": "week6reviewlink",
			"type": "LinkedServiceReference"
		},
		"annotations": [],
		"type": "DelimitedText",
		"typeProperties": {
			"location": {
				"type": "AzureBlobStorageLocation",
				"fileName": "house-prices.csv",
				"folderPath": "input",
				"container": "houseprice"
			},
			"columnDelimiter": ",",
			"escapeChar": "\\",
			"quoteChar": "\""
		},
		"schema": [
			{
				"type": "String"
			},
			{
				"type": "String"
			},
			{
				"type": "String"
			},
			{
				"type": "String"
			},
			{
				"type": "String"
			},
			{
				"type": "String"
			},
			{
				"type": "String"
			},
			{
				"type": "String"
			}
		]
	}
}